cpp_comment_format/__init__.py
cpp_comment_format/_version.py
cpp_comment_format-0.2.1.dist-info/LICENSE
cpp_comment_format-0.2.1.dist-info/METADATA
cpp_comment_format-0.2.1.dist-info/WHEEL
cpp_comment_format-0.2.1.dist-info/entry_points.txt
cpp_comment_format-0.2.1.dist-info/top_level.txt
cpp_comment_format-0.2.1.dist-info/RECORD
