Metadata-Version: 2.1
Name: cpp-comment-format
Version: 0.2.1
Summary: C++ comment formatter
Author-email: Tom de Geus <tom@geus.me>
Project-URL: Source, https://github.com/tdegeus/cpp_comment_format
Classifier: License :: OSI Approved :: MIT License
Requires-Python: >=3.6
License-File: LICENSE
Requires-Dist: pyyaml
